telethon_django/__init__.py
telethon_django/admin.py
telethon_django/apps.py
telethon_django/models.py
telethon_django/session.py
telethon_django/build/__init__.py
telethon_django/build/lib/__init__.py
telethon_django/build/lib/migrations/0001_initial.py
telethon_django/build/lib/migrations/__init__.py
telethon_django/migrations/0001_initial.py
telethon_django/migrations/0002_auto_20180826_1648.py
telethon_django/migrations/0003_auto_20180826_1708.py
telethon_django/migrations/__init__.py
telethon_django-0.1.4.dist-info/METADATA
telethon_django-0.1.4.dist-info/RECORD
telethon_django-0.1.4.dist-info/WHEEL
telethon_django-0.1.4.dist-info/top_level.txt
