Metadata-Version: 2.1
Name: telethon-django
Version: 0.1.4
Summary: Telethon Django helper (telethon-sync)
Home-page: https://github.com/TheUnravelGhoul/telethon-django/
Author: theunravelghoul
Author-email: densmorgon@gmail.com
License: BSD License
Platform: UNKNOWN
Classifier: Environment :: Web Environment
Classifier: Framework :: Django
Classifier: Intended Audience :: Developers
Classifier: License :: OSI Approved :: BSD License
Classifier: Operating System :: OS Independent
Classifier: Programming Language :: Python
Classifier: Programming Language :: Python :: 3.5
Classifier: Programming Language :: Python :: 3.6
Classifier: Topic :: Internet :: WWW/HTTP
Classifier: Topic :: Internet :: WWW/HTTP :: Dynamic Content
